kskimgeometry/__init__.py
kskimgeometry/circle.py
kskimgeometry/rectangle.py
kskimgeometry-0.1.dist-info/METADATA
kskimgeometry-0.1.dist-info/WHEEL
kskimgeometry-0.1.dist-info/top_level.txt
kskimgeometry-0.1.dist-info/RECORD
