Metadata-Version: 2.1
Name: kskimgeometry
Version: 0.1
Summary: A simple Python library for calculating the area of geometric shapes.
Author: kskim
